{
    "niv": {
        "branch": "master",
        "description": "Easy dependency management for Nix projects",
        "homepage": "https://github.com/nmattia/niv",
        "owner": "nmattia",
        "repo": "niv",
        "rev": "f73bf8d584148677b01859677a63191c31911eae",
        "sha256": "0jlmrx633jvqrqlyhlzpvdrnim128gc81q5psz2lpp2af8p8q9qs",
        "type": "tarball",
        "url": "https://github.com/nmattia/niv/archive/f73bf8d584148677b01859677a63191c31911eae.tar.gz",
        "url_template": "https://github.com/<owner>/<repo>/archive/<rev>.tar.gz"
    },
    "nixpkgs": {
        "branch": "nixos-unstable",
        "description": "Nix Packages collection",
        "homepage": null,
        "owner": "nixos",
        "repo": "nixpkgs",
        "rev": "029a5de08390bb03c3f44230b064fd1850c6658a",
        "sha256": "03fjkzhrs2avcvdabgm7a65rnyjaqbqdnv4q86qyjkkwg64g5m8x",
        "type": "tarball",
        "url": "https://github.com/nixos/nixpkgs/archive/029a5de08390bb03c3f44230b064fd1850c6658a.tar.gz",
        "url_template": "https://github.com/<owner>/<repo>/archive/<rev>.tar.gz"
    }
}
